{
	"m_AudioMixer": { "m_Collection": "resources-1.assets", "m_PathID": 3791 },
	"m_BypassEffects": false,
	"m_Children": [],
	"m_CorrespondingSourceObject": { "m_Collection": "resources-1.assets", "m_PathID": 0 },
	"m_Effects": [
		{ "m_Collection": "resources-1.assets", "m_PathID": 31 }
	],
	"m_GroupID": {
		"m_Data_0_": 1433703695,
		"m_Data_1_": 1077838748,
		"m_Data_2_": 3121147582,
		"m_Data_3_": 647679985
	},
	"m_HideFlags": 0,
	"m_Mute": false,
	"m_Name": "Music",
	"m_Pitch": {
		"m_Data_0_": 2730211023,
		"m_Data_1_": 1294076980,
		"m_Data_2_": 3011692433,
		"m_Data_3_": 2794623953
	},
	"m_PrefabAsset": { "m_Collection": "resources-1.assets", "m_PathID": 0 },
	"m_PrefabInstance": { "m_Collection": "resources-1.assets", "m_PathID": 0 },
	"m_Send": {
		"m_Data_0_": 554879475,
		"m_Data_1_": 1214478372,
		"m_Data_2_": 2133983882,
		"m_Data_3_": 247373552
	},
	"m_Solo": false,
	"m_UserColorIndex": 0,
	"m_Volume": {
		"m_Data_0_": 2563236557,
		"m_Data_1_": 1249331723,
		"m_Data_2_": 3821482167,
		"m_Data_3_": 4196882345
	}
}