{
	"m_AtlasName": "",
	"m_AtlasRD": {
		"m_AlphaTexture": { "m_Collection": "resources-1.assets", "m_PathID": 0 },
		"m_AtlasRectOffset": {
			"m_X": 0,
			"m_Y": 0
		},
		"m_Bindpose": [],
		"m_DownscaleMultiplier": 0,
		"m_IndexBuffer": "",
		"m_SecondaryTextures": [],
		"m_SettingsRaw": 0,
		"m_SubMeshes": [],
		"m_Texture": { "m_Collection": "resources-1.assets", "m_PathID": 0 },
		"m_TextureRect": {
			"m_Height": 0,
			"m_Width": 0,
			"m_X": 0,
			"m_Y": 0
		},
		"m_TextureRectOffset": {
			"m_X": 0,
			"m_Y": 0
		},
		"m_UvTransform": {
			"m_W": 0,
			"m_X": 0,
			"m_Y": 0,
			"m_Z": 0
		},
		"m_VertexData": {
			"m_Channels": [],
			"m_Data": "",
			"m_VertexCount": 0
		}
	},
	"m_AtlasTags": [],
	"m_Bones": [],
	"m_Border": {
		"m_W": 0,
		"m_X": 0,
		"m_Y": 0,
		"m_Z": 0
	},
	"m_CorrespondingSourceObject": { "m_Collection": "resources-1.assets", "m_PathID": 0 },
	"m_Extrude": 1,
	"m_HideFlags": 0,
	"m_IsPolygon": false,
	"m_Name": "ancient_wall_pieces_0000_a",
	"m_Offset": {
		"m_X": 0,
		"m_Y": 0
	},
	"m_PackingTag": "",
	"m_PhysicsShape": [
		[
			{
				"m_X": -0.1171875,
				"m_Y": -0.5703125
			},
			{
				"m_X": 0.0859375,
				"m_Y": -0.4609375
			},
			{
				"m_X": 0.2890625,
				"m_Y": -0.3984375
			},
			{
				"m_X": 0.6484375,
				"m_Y": -0.3203125
			},
			{
				"m_X": 0.8203125,
				"m_Y": -0.2578125
			},
			{
				"m_X": 1.0078125,
				"m_Y": -0.2265625
			},
			{
				"m_X": 1.1171875,
				"m_Y": -0.3203125
			},
			{
				"m_X": 1.4453125,
				"m_Y": -0.3828125
			},
			{
				"m_X": 1.5859375,
				"m_Y": -0.2421875
			},
			{
				"m_X": 1.6171875,
				"m_Y": -0.1640625
			},
			{
				"m_X": 1.7734375,
				"m_Y": -0.3515625
			},
			{
				"m_X": 2.1328125,
				"m_Y": -0.2578125
			},
			{
				"m_X": 2.1796875,
				"m_Y": -0.1953125
			},
			{
				"m_X": 2.1796875,
				"m_Y": 0.1484375
			},
			{
				"m_X": 2.0078125,
				"m_Y": 0.4609375
			},
			{
				"m_X": 1.8984375,
				"m_Y": 0.5390625
			},
			{
				"m_X": 1.8515625,
				"m_Y": 0.8046875
			},
			{
				"m_X": 1.8671875,
				"m_Y": 0.9765625
			},
			{
				"m_X": 1.7109375,
				"m_Y": 1.1015625
			},
			{
				"m_X": 1.4921875,
				"m_Y": 1.1328125
			},
			{
				"m_X": 0.7421875,
				"m_Y": 1.1328125
			},
			{
				"m_X": 0.1953125,
				"m_Y": 1.1171875
			},
			{
				"m_X": 0.1640625,
				"m_Y": 1.1328125
			},
			{
				"m_X": -0.8359375,
				"m_Y": 1.1328125
			},
			{
				"m_X": -0.9609375,
				"m_Y": 1.1171875
			},
			{
				"m_X": -1.6796875,
				"m_Y": 1.1171875
			},
			{
				"m_X": -1.9140625,
				"m_Y": 1.0859375
			},
			{
				"m_X": -2.0703125,
				"m_Y": 1.0546875
			},
			{
				"m_X": -2.1640625,
				"m_Y": 0.9921875
			},
			{
				"m_X": -2.1328125,
				"m_Y": 0.1640625
			},
			{
				"m_X": -2.1953125,
				"m_Y": -0.0078125
			},
			{
				"m_X": -2.1953125,
				"m_Y": -0.4765625
			},
			{
				"m_X": -1.9609375,
				"m_Y": -0.7109375
			},
			{
				"m_X": -1.9140625,
				"m_Y": -0.9765625
			},
			{
				"m_X": -1.7109375,
				"m_Y": -1.1328125
			},
			{
				"m_X": -1.5078125,
				"m_Y": -1.1328125
			},
			{
				"m_X": -0.6796875,
				"m_Y": -0.9296875
			},
			{
				"m_X": -0.4140625,
				"m_Y": -0.7421875
			},
			{
				"m_X": -0.2890625,
				"m_Y": -0.5703125
			}
		],
		[
			{
				"m_X": -1.0703125,
				"m_Y": -0.2265625
			},
			{
				"m_X": -1.0703125,
				"m_Y": -0.1484375
			},
			{
				"m_X": -0.7890625,
				"m_Y": -0.1171875
			},
			{
				"m_X": -0.7890625,
				"m_Y": -0.0859375
			},
			{
				"m_X": -0.7421875,
				"m_Y": -0.0859375
			},
			{
				"m_X": -0.7265625,
				"m_Y": -0.0703125
			},
			{
				"m_X": -0.7421875,
				"m_Y": -0.0703125
			},
			{
				"m_X": -0.7421875,
				"m_Y": -0.1953125
			},
			{
				"m_X": -0.7578125,
				"m_Y": -0.2109375
			},
			{
				"m_X": -0.9296875,
				"m_Y": -0.1953125
			},
			{
				"m_X": -0.9609375,
				"m_Y": -0.1953125
			},
			{
				"m_X": -1.0390625,
				"m_Y": -0.2109375
			},
			{
				"m_X": -1.0859375,
				"m_Y": -0.2421875
			}
		],
		[
			{
				"m_X": -1.4921875,
				"m_Y": 0.1953125
			},
			{
				"m_X": -1.4609375,
				"m_Y": 0.1796875
			},
			{
				"m_X": -1.4921875,
				"m_Y": 0.1953125
			},
			{
				"m_X": -1.5078125,
				"m_Y": 0.1796875
			},
			{
				"m_X": -1.4921875,
				"m_Y": 0.1796875
			}
		]
	],
	"m_Pivot": {
		"m_X": 0.5,
		"m_Y": 0.5
	},
	"m_PixelsToUnits": 64,
	"m_PrefabAsset": { "m_Collection": "resources-1.assets", "m_PathID": 0 },
	"m_PrefabInstance": { "m_Collection": "resources-1.assets", "m_PathID": 0 },
	"m_RD": {
		"m_AlphaTexture": { "m_Collection": "resources-1.assets", "m_PathID": 0 },
		"m_AtlasRectOffset": {
			"m_X": 916,
			"m_Y": 2682
		},
		"m_Bindpose": [],
		"m_DownscaleMultiplier": 1,
		"m_IndexBuffer": "FgAVABIAFAASABUAEQASABQAEwASABEAEAAPAA4ACwAOAA8ADAAOAAsADQAMAAsACgAJAAgAAAAIAAkABwAIAAAABgAHAAAABQAGAAAABAAFAAAAAwAEAAAAAQADAAAAAgABAAAA",
		"m_SecondaryTextures": [],
		"m_SettingsRaw": 65,
		"m_SubMeshes": [
			{
				"m_BaseVertex": 0,
				"m_FirstByte": 0,
				"m_FirstVertex": 0,
				"m_IndexCount": 51,
				"m_LocalAABB": {
					"m_Center": {
						"m_X": 0,
						"m_Y": 0,
						"m_Z": 0
					},
					"m_Extent": {
						"m_X": 0,
						"m_Y": 0,
						"m_Z": 0
					}
				},
				"m_Topology": 0,
				"m_VertexCount": 23
			}
		],
		"m_Texture": { "m_Collection": "resources-1.assets", "m_PathID": 204 },
		"m_TextureRect": {
			"m_Height": 145,
			"m_Width": 281,
			"m_X": 916,
			"m_Y": 2682
		},
		"m_TextureRectOffset": {
			"m_X": 0,
			"m_Y": 0
		},
		"m_UvTransform": {
			"m_W": 2754.5,
			"m_X": 64,
			"m_Y": 1056.5,
			"m_Z": 64
		},
		"m_VertexData": {
			"m_Channels": [
				{
					"m_Dimension": 3,
					"m_Format": 0,
					"m_Offset": 0,
					"m_Stream": 0
				},
				{
					"m_Dimension": 0,
					"m_Format": 0,
					"m_Offset": 0,
					"m_Stream": 0
				},
				{
					"m_Dimension": 0,
					"m_Format": 0,
					"m_Offset": 0,
					"m_Stream": 0
				},
				{
					"m_Dimension": 0,
					"m_Format": 0,
					"m_Offset": 0,
					"m_Stream": 0
				},
				{
					"m_Dimension": 2,
					"m_Format": 0,
					"m_Offset": 0,
					"m_Stream": 1
				},
				{
					"m_Dimension": 0,
					"m_Format": 0,
					"m_Offset": 0,
					"m_Stream": 0
				},
				{
					"m_Dimension": 0,
					"m_Format": 0,
					"m_Offset": 0,
					"m_Stream": 0
				},
				{
					"m_Dimension": 0,
					"m_Format": 0,
					"m_Offset": 0,
					"m_Stream": 0
				},
				{
					"m_Dimension": 0,
					"m_Format": 0,
					"m_Offset": 0,
					"m_Stream": 0
				},
				{
					"m_Dimension": 0,
					"m_Format": 0,
					"m_Offset": 0,
					"m_Stream": 0
				},
				{
					"m_Dimension": 0,
					"m_Format": 0,
					"m_Offset": 0,
					"m_Stream": 0
				},
				{
					"m_Dimension": 0,
					"m_Format": 0,
					"m_Offset": 0,
					"m_Stream": 0
				},
				{
					"m_Dimension": 0,
					"m_Format": 0,
					"m_Offset": 0,
					"m_Stream": 0
				},
				{
					"m_Dimension": 0,
					"m_Format": 0,
					"m_Offset": 0,
					"m_Stream": 0
				}
			],
			"m_Data": "AAD7PwAAkT8AAAAAAIAMQAAAvL4AAAAAAIAMQAAA3D4AAAAAAAD1PwAA/L4AAAAAAACdPwAA9L4AAAAAAADcvgAAWr8AAAAAAAAyvwAAer8AAAAAAACXvwAAkb8AAAAAAADtvwAAkb8AAAAAAIAMwAAAkT8AAAAAAIAMwAAAKr8AAAAAAIAKQAAAej8AAAAAAIAMQAAAYj8AAAAAAIAMQAAAdj8AAAAAAIAJQAAAXj8AAAAAAIAHQAAAbj8AAAAAAIAHQAAAZj8AAAAAAIAMQAAAkT8AAAAAAIALQAAAgT8AAAAAAIAMQAAAgT8AAAAAAIAKQAAAkT8AAAAAAIAIQAAAjT8AAAAAAIAIQAAAhz8AAAAAAAAAAAAAAAAAAAAAAAAAAAAAAAAAAAAAAAAAAAAAAAAAAAAAAAAAAAAAAAAAAAAAAAAAAAAAAAAAAAAAAAAAAAAAAAAAAAAAAAAAAAAAAAAAAAAAAAAAAAAAAAAAAAAAAAAAAAAAAAAAAAAAAAAAAAAAAAAAAAAAAAAAAAAAAAAAAAAAAAAAAAAAAAAAAAAAAAAAAAAAAAAAAAAAAAAAAAAAAAAAAAAAAAAAAAAAAAAAAAAAAAAAAAAAAAAAAAAAAAAAAA==",
			"m_VertexCount": 23
		}
	},
	"m_Rect": {
		"m_Height": 145,
		"m_Width": 281,
		"m_X": 916,
		"m_Y": 2682
	},
	"m_RenderDataKey": {
		"Key": {
			"m_Data_0_": 3937697036,
			"m_Data_1_": 1282298867,
			"m_Data_2_": 2348460968,
			"m_Data_3_": 3788168378
		},
		"Value": 21300000
	},
	"m_SpriteAtlas": { "m_Collection": "resources-1.assets", "m_PathID": 0 },
	"m_SpriteID": ""
}